basicgates.v
module and1(a,b,c);
    input wire a,b;
    output wire c;
    assign c = a & b;
endmodule

module or1(a,b,c);
    input wire a,b;
    output wire c;
    assign c = a | b;
endmodule

module not1(a,c);
    input wire a;
    output wire c;
    assign c = ~a;
endmodule

module xor1(a,b,c);
    input wire a,b;
    output wire c;
    assign c = a ^ b;
endmodule

adder.v
module fulladder(a,b,cin,s,cy);
    input wire a,b,cin;
    output wire s,cy;
    wire x,y,z;

    xor1 x1(a,b,x);
    and1 a1(a,b,y);
    xor1 x2(cin,x,s);
    and1 a2(cin,x,z);
    or1 o1(z,y,cy);

endmodule

test.v
module tb;
    reg a;
    reg b;
    reg c;
    wire x,y;
    fulladder f1(a,b,c,x,y);

    initial begin
        $dumpfile("dump.vcd");
        $dumpvars(0,tb);
    end
    initial begin
        $monitor(a,b,c,x,y);
        a = 1'b0;
        b = 1'b0;
        c = 1'b0;
        #10
        a = 1'b0;
        b = 1'b0;
        c = 1'b1;
        #10
        a = 1'b0;
        b = 1'b1;
        c = 1'b0;
        #10
        a = 1'b0;
        b = 1'b1;
        c = 1'b1;
        #10
        a = 1'b1;
        b = 1'b0;
        c = 1'b0;
        #10
        a = 1'b1;
        b = 1'b0;
        c = 1'b1;
        #10
        a = 1'b1;
        b = 1'b1;
        c = 1'b0;
        #10
        a = 1'b1;
        b = 1'b1;
        c = 1'b1;
    end
endmodule

dump.vcd
$date
	Thu Aug 18 14:08:54 2022
$end
$version
	Icarus Verilog
$end
$timescale
	1s
$end
$scope module tb $end
$var wire 1 ! y $end
$var wire 1 " x $end
$var reg 1 # a $end
$var reg 1 $ b $end
$var reg 1 % c $end
$scope module f1 $end
$var wire 1 # a $end
$var wire 1 $ b $end
$var wire 1 % cin $end
$var wire 1 & z $end
$var wire 1 ' y $end
$var wire 1 ( x $end
$var wire 1 " s $end
$var wire 1 ! cy $end
$scope module a1 $end
$var wire 1 # a $end
$var wire 1 $ b $end
$var wire 1 ' c $end
$upscope $end
$scope module a2 $end
$var wire 1 % a $end
$var wire 1 & c $end
$var wire 1 ( b $end
$upscope $end
$scope module o1 $end
$var wire 1 & a $end
$var wire 1 ' b $end
$var wire 1 ! c $end
$upscope $end
$scope module x1 $end
$var wire 1 # a $end
$var wire 1 $ b $end
$var wire 1 ( c $end
$upscope $end
$scope module x2 $end
$var wire 1 % a $end
$var wire 1 ( b $end
$var wire 1 " c $end
$upscope $end
$upscope $end
$upscope $end
$enddefinitions $end
$comment Show the parameter values. $end
$dumpall
$end
#0
$dumpvars
0(
0'
0&
0%
0$
0#
0"
0!
$end
#10
1"
1%
#20
1(
0%
1$
#30
1!
1&
0"
1%
#40
0!
0&
1"
0%
0$
1#
#50
1!
1&
0"
1%
#60
0&
1'
0(
0%
1$
#70
1"
1%
