demux.v
module demux(i0,i1,i2,i3,i4,i5,i6,i7,s2,s1,s0,o);
    input wire i0,i1,i2,i3,i4,i5,i6,i7,s2,s1,s0;
    output wire o;

    assign o = ((~s2)&(~s1)&(~s0)&i0) | ((~s2)&(~s1)&(s0)&i1) | ((~s2)&(s1)&(~s0)&i2) | ((~s2)&(s1)&(s0)&i3) | ((s2)&(~s1)&(~s0)&i4) | ((s2)&(~s1)&(s0)&i5) | ((s2)&(s1)&(~s0)&i6) | ((s2)&(s1)&(s0)&i7);
endmodule

test_demux.v
module tb;
    reg [7:0]inp;
    reg [2:0]sel;
    wire o;
    demux f1(inp[7],inp[6],inp[5],inp[4],inp[3],inp[2],inp[1],inp[0],sel[2],sel[1],sel[0],o);

    initial begin
        $dumpfile("dump.vcd");
        $dumpvars(0,tb);
    end

    initial begin
        $monitor("%b %b %b %b %b %b %b %b %b %b ",inp[7],inp[6],inp[5],inp[4],inp[3],inp[2],inp[1],inp[0],sel,o);

        inp = 8'b01010101;
        sel = 3'b000;
        #10
        sel = 3'b001;
        #10
        sel = 3'b010;
        #10
        sel = 3'b011;
        #10
        sel = 3'b100;
        #10
        sel = 3'b101;
        #10
        sel = 3'b110;
        #10
        sel = 3'b111;
        
    end
endmodule

dump.vcd
$date
	Sat Aug 27 19:03:54 2022
$end
$version
	Icarus Verilog
$end
$timescale
	1s
$end
$scope module tb $end
$var wire 1 ! o $end
$var reg 8 " inp [7:0] $end
$var reg 3 # sel [2:0] $end
$scope module f1 $end
$var wire 1 $ i0 $end
$var wire 1 % i1 $end
$var wire 1 & i2 $end
$var wire 1 ' i3 $end
$var wire 1 ( i4 $end
$var wire 1 ) i5 $end
$var wire 1 * i6 $end
$var wire 1 + i7 $end
$var wire 1 ! o $end
$var wire 1 , s0 $end
$var wire 1 - s1 $end
$var wire 1 . s2 $end
$upscope $end
$upscope $end
$enddefinitions $end
$comment Show the parameter values. $end
$dumpall
$end
#0
$dumpvars
0.
0-
0,
1+
0*
1)
0(
1'
0&
1%
0$
b0 #
b1010101 "
0!
$end
#10
1!
1,
b1 #
#20
0!
1-
0,
b10 #
#30
1!
1,
b11 #
#40
0!
1.
0-
0,
b100 #
#50
1!
1,
b101 #
#60
0!
1-
0,
b110 #
#70
1!
1,
b111 #
